manta/__init__.py
manta/cli.py
manta/config.py
manta/manta_entry.py
manta/optimization_entry.py
manta/_functions/__init__.py
manta/_functions/common_language/__init__.py
manta/_functions/common_language/emoji_processor.py
manta/_functions/common_language/ngram_bpe.py
manta/_functions/common_language/ngram_tokenizer_wrapper.py
manta/_functions/common_language/ngram_wordpiece.py
manta/_functions/common_language/topic_extractor.py
manta/_functions/english/__init__.py
manta/_functions/english/english_entry.py
manta/_functions/english/english_nmf_core.py
manta/_functions/english/english_preprocessor.py
manta/_functions/english/english_text_encoder.py
manta/_functions/english/english_topic_analyzer.py
manta/_functions/english/english_topic_output.py
manta/_functions/english/english_vocabulary.py
manta/_functions/nmf/__init__.py
manta/_functions/nmf/nmf_basic.py
manta/_functions/nmf/nmf_initialization.py
manta/_functions/nmf/nmf_orchestrator.py
manta/_functions/nmf/nmf_projective_basic.py
manta/_functions/nmf/nmf_projective_enhanced.py
manta/_functions/nmf/nmtf/__init__.py
manta/_functions/nmf/nmtf/example_usage.py
manta/_functions/nmf/nmtf/extract_nmtf_topics.py
manta/_functions/nmf/nmtf/nmtf.py
manta/_functions/nmf/nmtf/nmtf_init.py
manta/_functions/nmf/nmtf/nmtf_util.py
manta/_functions/nmf/other/hierarchical_nmf.py
manta/_functions/nmf/other/nmf_onlineNMF.py
manta/_functions/nmf/other/symmetric_nmf.py
manta/_functions/tfidf/__init__.py
manta/_functions/tfidf/tfidf_bm25_turkish.py
manta/_functions/tfidf/tfidf_english_calculator.py
manta/_functions/tfidf/tfidf_idf_functions.py
manta/_functions/tfidf/tfidf_tf_functions.py
manta/_functions/tfidf/tfidf_turkish_calculator.py
manta/_functions/turkish/__init__.py
manta/_functions/turkish/turkish_entry.py
manta/_functions/turkish/turkish_preprocessor.py
manta/_functions/turkish/turkish_text_encoder.py
manta/_functions/turkish/turkish_tokenizer_factory.py
manta/pipeline/__init__.py
manta/pipeline/data_pipeline.py
manta_topic_modelling-0.9.1.dist-info/licenses/LICENSE
manta_topic_modelling-0.9.1.dist-info/METADATA
manta_topic_modelling-0.9.1.dist-info/WHEEL
manta_topic_modelling-0.9.1.dist-info/entry_points.txt
manta_topic_modelling-0.9.1.dist-info/top_level.txt
manta_topic_modelling-0.9.1.dist-info/RECORD
